my_package_jorgerodmos/__init__.py
my_package_jorgerodmos/r_primes.py
my_package_jorgerodmos-1.0.1.dist-info/METADATA
my_package_jorgerodmos-1.0.1.dist-info/WHEEL
my_package_jorgerodmos-1.0.1.dist-info/top_level.txt
my_package_jorgerodmos-1.0.1.dist-info/RECORD
