Metadata-Version: 2.1
Name: my-package-jorgerodmos
Version: 1.0.1
Summary: Python Prime numbers with R
Home-page: UNKNOWN
Author: Jorge Rodriguez
Author-email: jorgerodmos04@gmail.com
License: UNKNOWN
Platform: UNKNOWN
Requires-Python: >=3.9.2
